sgnllai/__init__.py
sgnllai/_version.py
sgnllai/bin/__init__.py
sgnllai/bin/run_bayestar.py
sgnllai/bin/run_mock_publisher.py
sgnllai/bin/run_superevent.py
sgnllai/gracedb/__init__.py
sgnllai/gracedb/client.py
sgnllai/gracedb/mixin.py
sgnllai/gracedb/utils.py
sgnllai/pipelines/__init__.py
sgnllai/sinks/__init__.py
sgnllai/sinks/gracedb_event_sink.py
sgnllai/sinks/gracedb_sink.py
sgnllai/transforms/__init__.py
sgnllai/transforms/bayestar_processor.py
sgnllai/transforms/gracedb_uploader.py
sgnllai/transforms/skymap_plotter.py
sgnllai/transforms/superevent_creator.py
sgnllai-0.1.1.dist-info/METADATA
sgnllai-0.1.1.dist-info/WHEEL
sgnllai-0.1.1.dist-info/entry_points.txt
sgnllai-0.1.1.dist-info/top_level.txt
sgnllai-0.1.1.dist-info/RECORD
