Metadata-Version: 2.4
Name: sgnllai
Version: 0.1.1
Summary: SGN pipeline for GW superevent creation with GraceDB integration
Author-email: Chad Hanna <crh184@psu.edu>
License: MPL-2.0
Classifier: Programming Language :: Python :: 3
Classifier: License :: OSI Approved :: Mozilla Public License 2.0 (MPL 2.0)
Classifier: Operating System :: OS Independent
Requires-Python: >=3.11
Requires-Dist: sgn-skig>=0.1
Requires-Dist: sgn>=0.5
Requires-Dist: sgn-ts>=0.5
Requires-Dist: sgn-ligo>=0.2
Requires-Dist: ligo-gracedb>=2.0
Requires-Dist: ligo.skymap>=2.5
Requires-Dist: astropy>=7.0
Requires-Dist: matplotlib>=3.0
Provides-Extra: test
Requires-Dist: pytest; extra == "test"
Requires-Dist: pytest-cov; extra == "test"
Requires-Dist: pytest-asyncio; extra == "test"
Provides-Extra: lint
Requires-Dist: black; extra == "lint"
Requires-Dist: flake8; extra == "lint"
Requires-Dist: flake8-bandit; extra == "lint"
Requires-Dist: flake8-black; extra == "lint"
Requires-Dist: flake8-bugbear; extra == "lint"
Requires-Dist: flake8-future-annotations; extra == "lint"
Requires-Dist: flake8-isort; extra == "lint"
Requires-Dist: flake8-logging-format; extra == "lint"
Requires-Dist: flake8-pyproject; extra == "lint"
Requires-Dist: isort; extra == "lint"
Requires-Dist: mypy; extra == "lint"
Requires-Dist: mypy-extensions; extra == "lint"
Requires-Dist: typing_extensions; extra == "lint"
Provides-Extra: dev
Requires-Dist: sgnllai[lint]; extra == "dev"
Requires-Dist: sgnllai[test]; extra == "dev"
